django_webpack_helper-0.2.2.dist-info/DESCRIPTION.rst
django_webpack_helper-0.2.2.dist-info/METADATA
django_webpack_helper-0.2.2.dist-info/RECORD
django_webpack_helper-0.2.2.dist-info/WHEEL
django_webpack_helper-0.2.2.dist-info/metadata.json
django_webpack_helper-0.2.2.dist-info/top_level.txt
webpack_helper/__init__.py
webpack_helper/apps.py
webpack_helper/conf.py
webpack_helper/index.js
webpack_helper/package.json
webpack_helper/management/__init__.py
webpack_helper/management/commands/__init__.py
webpack_helper/management/commands/gen_webpack_config.py
webpack_helper/management/commands/npm_install.py
webpack_helper/management/commands/webpack.config.js
webpack_helper/management/commands/webpack_helper.py
webpack_helper/management/commands/webpackh.py
